{
  "args": {
    "variant_name": "smoke_oracle_primitive_router",
    "seed": 83,
    "device": "auto",
    "modulus": 7,
    "observe_mod": 3,
    "observe_prob": 0.3,
    "op_family": "full",
    "query_family": "all",
    "slot_capacity": 7,
    "init_mode": "oracle",
    "transition_mode": "primitive_router",
    "supervision": "full_belief",
    "slot_dim": 64,
    "hidden_dim": 128,
    "fourier_order": 8,
    "init_logit_scale": 8.0,
    "temperature": 1.0,
    "train_min_len": 1,
    "train_max_len": 3,
    "eval_lengths": "2,3",
    "eval_k": "0,1,2,3",
    "eval_query_types": "all",
    "train_steps": 500,
    "batch_size": 128,
    "eval_batch_size": 128,
    "eval_examples": 128,
    "lr": 0.001,
    "weight_decay": 0.0001,
    "belief_loss_weight": 1.0,
    "query_loss_weight": 0.0,
    "slot_entropy_weight": 0.003,
    "init_coverage_loss_weight": 0.0,
    "init_relation_loss_weight": 0.0,
    "init_weight_uniform_loss_weight": 0.0,
    "init_slot_overlap_loss_weight": 0.0,
    "max_grad_norm": 1.0,
    "log_every": 100,
    "output_dir": "experiments/end_to_end_structured_slot_executor/runs/smoke_oracle_primitive_router",
    "checkpoint_dir": ""
  },
  "train": [
    {
      "step": 1,
      "loss": 3.0614840984344482,
      "grad_norm": 0.1815788894891739,
      "elapsed_seconds": 0.6142785549163818,
      "mean_slot_purity": 0.25913116335868835,
      "mean_weight_entropy": 1.6344691514968872,
      "mean_route_entropy": 2.300720453262329,
      "mean_route_accuracy": 0.15625,
      "belief_loss": 3.0563933849334717,
      "slot_entropy_loss": 1.6969051361083984,
      "init_belief_target_mass": 0.9999985694885254,
      "init_belief_target_nll": 1.9459115266799927,
      "init_belief_top1_on_support": 1.0,
      "init_slot_relation_accuracy": 1.0,
      "init_slot_unique_a_frac": 1.0,
      "init_mixture_a_entropy": 1.945910096168518,
      "init_mixture_b_entropy": 1.945910096168518,
      "init_slot_a_overlap": 2.2507009589389781e-07,
      "init_slot_b_overlap": 2.2507009589389781e-07,
      "decoder_belief_target_mass": 0.1749340295791626,
      "decoder_belief_target_nll": 3.65116548538208,
      "decoder_belief_top1_on_support": 0.2421875,
      "mean_decoder_belief_support_size": 4.9453125,
      "decoder_query_target_mass": 0.6553540229797363,
      "decoder_query_target_nll": 1.920073390007019,
      "decoder_query_top1_on_support": 0.6875,
      "mean_decoder_query_support_size": 4.3046875
    },
    {
      "step": 100,
      "loss": 1.6147269010543823,
      "grad_norm": 0.0013708308106288314,
      "elapsed_seconds": 27.127522945404053,
      "mean_slot_purity": 0.8579589128494263,
      "mean_weight_entropy": 1.4010488986968994,
      "mean_route_entropy": 0.0016359626315534115,
      "mean_route_accuracy": 1.0,
      "belief_loss": 1.6142960786819458,
      "slot_entropy_loss": 0.14359337091445923,
      "init_belief_target_mass": 0.9999985694885254,
      "init_belief_target_nll": 1.9459115266799927,
      "init_belief_top1_on_support": 1.0,
      "init_slot_relation_accuracy": 1.0,
      "init_slot_unique_a_frac": 1.0,
      "init_mixture_a_entropy": 1.945910096168518,
      "init_mixture_b_entropy": 1.945910096168518,
      "init_slot_a_overlap": 2.2507009589389781e-07,
      "init_slot_b_overlap": 2.2507009589389781e-07,
      "decoder_belief_target_mass": 0.9996786117553711,
      "decoder_belief_target_nll": 1.401260495185852,
      "decoder_belief_top1_on_support": 1.0,
      "mean_decoder_belief_support_size": 4.8125,
      "decoder_query_target_mass": 0.9998814463615417,
      "decoder_query_target_nll": 1.1418952941894531,
      "decoder_query_top1_on_support": 1.0,
      "mean_decoder_query_support_size": 4.1328125
    },
    {
      "step": 200,
      "loss": 1.6680614948272705,
      "grad_norm": 0.000988794257864356,
      "elapsed_seconds": 53.88230061531067,
      "mean_slot_purity": 0.8825878500938416,
      "mean_weight_entropy": 1.461085557937622,
      "mean_route_entropy": 0.00113393715582788,
      "mean_route_accuracy": 1.0,
      "belief_loss": 1.667716145515442,
      "slot_entropy_loss": 0.11511082202196121,
      "init_belief_target_mass": 0.9999985694885254,
      "init_belief_target_nll": 1.9459115266799927,
      "init_belief_top1_on_support": 1.0,
      "init_slot_relation_accuracy": 1.0,
      "init_slot_unique_a_frac": 1.0,
      "init_mixture_a_entropy": 1.945910096168518,
      "init_mixture_b_entropy": 1.945910096168518,
      "init_slot_a_overlap": 2.2507009589389781e-07,
      "init_slot_b_overlap": 2.2507009589389781e-07,
      "decoder_belief_target_mass": 0.9997850656509399,
      "decoder_belief_target_nll": 1.4612045288085938,
      "decoder_belief_top1_on_support": 1.0,
      "mean_decoder_belief_support_size": 5.0390625,
      "decoder_query_target_mass": 0.999937891960144,
      "decoder_query_target_nll": 1.2559185028076172,
      "decoder_query_top1_on_support": 1.0,
      "mean_decoder_query_support_size": 4.46875
    },
    {
      "step": 300,
      "loss": 1.6225879192352295,
      "grad_norm": 0.00044303841423243284,
      "elapsed_seconds": 80.52338361740112,
      "mean_slot_purity": 0.8635493516921997,
      "mean_weight_entropy": 1.3268496990203857,
      "mean_route_entropy": 0.0006749664898961782,
      "mean_route_accuracy": 1.0,
      "belief_loss": 1.6221818923950195,
      "slot_entropy_loss": 0.1353449821472168,
      "init_belief_target_mass": 0.9999985694885254,
      "init_belief_target_nll": 1.9459115266799927,
      "init_belief_top1_on_support": 1.0,
      "init_slot_relation_accuracy": 1.0,
      "init_slot_unique_a_frac": 1.0,
      "init_mixture_a_entropy": 1.945910096168518,
      "init_mixture_b_entropy": 1.945910096168518,
      "init_slot_a_overlap": 2.2507009589389781e-07,
      "init_slot_b_overlap": 2.2507009589389781e-07,
      "decoder_belief_target_mass": 0.9998689889907837,
      "decoder_belief_target_nll": 1.3268601894378662,
      "decoder_belief_top1_on_support": 1.0,
      "mean_decoder_belief_support_size": 4.515625,
      "decoder_query_target_mass": 0.9999449849128723,
      "decoder_query_target_nll": 1.1535440683364868,
      "decoder_query_top1_on_support": 1.0,
      "mean_decoder_query_support_size": 4.078125
    },
    {
      "step": 400,
      "loss": 1.634432315826416,
      "grad_norm": 0.00042698413017205894,
      "elapsed_seconds": 106.9196093082428,
      "mean_slot_purity": 0.853837251663208,
      "mean_weight_entropy": 1.4660557508468628,
      "mean_route_entropy": 0.0006085592322051525,
      "mean_route_accuracy": 1.0,
      "belief_loss": 1.633945345878601,
      "slot_entropy_loss": 0.1623370498418808,
      "init_belief_target_mass": 0.9999985694885254,
      "init_belief_target_nll": 1.9459115266799927,
      "init_belief_top1_on_support": 1.0,
      "init_slot_relation_accuracy": 1.0,
      "init_slot_unique_a_frac": 1.0,
      "init_mixture_a_entropy": 1.945910096168518,
      "init_mixture_b_entropy": 1.945910096168518,
      "init_slot_a_overlap": 2.2507009589389781e-07,
      "init_slot_b_overlap": 2.2507009589389781e-07,
      "decoder_belief_target_mass": 0.9998915195465088,
      "decoder_belief_target_nll": 1.4661060571670532,
      "decoder_belief_top1_on_support": 1.0,
      "mean_decoder_belief_support_size": 5.0625,
      "decoder_query_target_mass": 0.9999501705169678,
      "decoder_query_target_nll": 1.0885565280914307,
      "decoder_query_top1_on_support": 1.0,
      "mean_decoder_query_support_size": 3.984375
    },
    {
      "step": 500,
      "loss": 1.614986538887024,
      "grad_norm": 0.00030064122984185815,
      "elapsed_seconds": 133.33737516403198,
      "mean_slot_purity": 0.8562918901443481,
      "mean_weight_entropy": 1.410771369934082,
      "mean_route_entropy": 0.00048823439283296466,
      "mean_route_accuracy": 1.0,
      "belief_loss": 1.614521861076355,
      "slot_entropy_loss": 0.1548759639263153,
      "init_belief_target_mass": 0.9999985694885254,
      "init_belief_target_nll": 1.9459115266799927,
      "init_belief_top1_on_support": 1.0,
      "init_slot_relation_accuracy": 1.0,
      "init_slot_unique_a_frac": 1.0,
      "init_mixture_a_entropy": 1.945910096168518,
      "init_mixture_b_entropy": 1.945910096168518,
      "init_slot_a_overlap": 2.2507009589389781e-07,
      "init_slot_b_overlap": 2.2507009589389781e-07,
      "decoder_belief_target_mass": 0.9999203085899353,
      "decoder_belief_target_nll": 1.4108057022094727,
      "decoder_belief_top1_on_support": 1.0,
      "mean_decoder_belief_support_size": 4.8515625,
      "decoder_query_target_mass": 0.9999712705612183,
      "decoder_query_target_nll": 1.1894991397857666,
      "decoder_query_top1_on_support": 1.0,
      "mean_decoder_query_support_size": 4.2265625
    }
  ],
  "eval": [
    {
      "step": 500,
      "rows": [
        {
          "model": "end_to_end_structured_slot_executor",
          "variant": "smoke_oracle_primitive_router",
          "modulus": 7,
          "observe_mod": 3,
          "observe_prob": 0.3,
          "op_family": "full",
          "query_family": "all",
          "slot_capacity": 7,
          "init_mode": "oracle",
          "transition_mode": "primitive_router",
          "supervision": "full_belief",
          "slot_dim": 64,
          "hidden_dim": 128,
          "fourier_order": 8,
          "train_steps": 500,
          "length": 2,
          "query_type": "A",
          "k": 0,
          "n": 128,
          "decoder_query_target_mass": 0.6171875,
          "decoder_query_target_nll": 1.9459102153778076,
          "decoder_query_top1_on_support": 0.6171875,
          "mean_decoder_query_support_size": 4.3203125,
          "decoder_belief_target_mass": 0.14843741059303284,
          "decoder_belief_target_nll": 13.83605670928955,
          "decoder_belief_top1_on_support": 0.2578125,
          "mean_decoder_belief_support_size": 4.953125,
          "init_belief_target_mass": 0.9999985694885254,
          "init_belief_target_nll": 1.9459115266799927,
          "init_belief_top1_on_support": 1.0,
          "init_slot_relation_accuracy": 1.0,
          "init_slot_unique_a_frac": 1.0,
          "init_mixture_a_entropy": 1.945910096168518,
          "init_mixture_b_entropy": 1.945910096168518,
          "init_slot_a_overlap": 2.2507009589389781e-07,
          "init_slot_b_overlap": 2.2507009589389781e-07,
          "mean_slot_purity": 0.9999986290931702,
          "mean_slot_entropy": 2.3037249775370583e-05,
          "mean_weight_entropy": 1.9459102153778076,
          "mean_route_entropy": -1.0,
          "mean_route_accuracy": -1.0,
          "mean_target_support_size": 4.953125
        },
        {
          "model": "end_to_end_structured_slot_executor",
          "variant": "smoke_oracle_primitive_router",
          "modulus": 7,
          "observe_mod": 3,
          "observe_prob": 0.3,
          "op_family": "full",
          "query_family": "all",
          "slot_capacity": 7,
          "init_mode": "oracle",
          "transition_mode": "primitive_router",
          "supervision": "full_belief",
          "slot_dim": 64,
          "hidden_dim": 128,
          "fourier_order": 8,
          "train_steps": 500,
          "length": 2,
          "query_type": "A",
          "k": 1,
          "n": 128,
          "decoder_query_target_mass": 0.7795735597610474,
          "decoder_query_target_nll": 2.5520200729370117,
          "decoder_query_top1_on_support": 0.8046875,
          "mean_decoder_query_support_size": 4.3203125,
          "decoder_belief_target_mass": 0.2912924289703369,
          "decoder_belief_target_nll": 9.614702224731445,
          "decoder_belief_top1_on_support": 0.3828125,
          "mean_decoder_belief_support_size": 4.953125,
          "init_belief_target_mass": 0.9999985694885254,
          "init_belief_target_nll": 1.9459115266799927,
          "init_belief_top1_on_support": 1.0,
          "init_slot_relation_accuracy": 1.0,
          "init_slot_unique_a_frac": 1.0,
          "init_mixture_a_entropy": 1.945910096168518,
          "init_mixture_b_entropy": 1.945910096168518,
          "init_slot_a_overlap": 2.2507009589389781e-07,
          "init_slot_b_overlap": 2.2507009589389781e-07,
          "mean_slot_purity": 0.8969155550003052,
          "mean_slot_entropy": 0.1542171984910965,
          "mean_weight_entropy": 1.6379207372665405,
          "mean_route_entropy": 0.0004337792925070971,
          "mean_route_accuracy": 1.0,
          "mean_target_support_size": 4.953125
        },
        {
          "model": "end_to_end_structured_slot_executor",
          "variant": "smoke_oracle_primitive_router",
          "modulus": 7,
          "observe_mod": 3,
          "observe_prob": 0.3,
          "op_family": "full",
          "query_family": "all",
          "slot_capacity": 7,
          "init_mode": "oracle",
          "transition_mode": "primitive_router",
          "supervision": "full_belief",
          "slot_dim": 64,
          "hidden_dim": 128,
          "fourier_order": 8,
          "train_steps": 500,
          "length": 2,
          "query_type": "A",
          "k": 2,
          "n": 128,
          "decoder_query_target_mass": 0.9999849796295166,
          "decoder_query_target_nll": 1.2342402935028076,
          "decoder_query_top1_on_support": 1.0,
          "mean_decoder_query_support_size": 4.3203125,
          "decoder_belief_target_mass": 0.9999264478683472,
          "decoder_belief_target_nll": 1.456474781036377,
          "decoder_belief_top1_on_support": 1.0,
          "mean_decoder_belief_support_size": 4.953125,
          "init_belief_target_mass": 0.9999985694885254,
          "init_belief_target_nll": 1.9459115266799927,
          "init_belief_top1_on_support": 1.0,
          "init_slot_relation_accuracy": 1.0,
          "init_slot_unique_a_frac": 1.0,
          "init_mixture_a_entropy": 1.945910096168518,
          "init_mixture_b_entropy": 1.945910096168518,
          "init_slot_a_overlap": 2.2507009589389781e-07,
          "init_slot_b_overlap": 2.2507009589389781e-07,
          "mean_slot_purity": 0.8536256551742554,
          "mean_slot_entropy": 0.2611013650894165,
          "mean_weight_entropy": 1.4564307928085327,
          "mean_route_entropy": 0.00047736172564327717,
          "mean_route_accuracy": 1.0,
          "mean_target_support_size": 4.953125
        },
        {
          "model": "end_to_end_structured_slot_executor",
          "variant": "smoke_oracle_primitive_router",
          "modulus": 7,
          "observe_mod": 3,
          "observe_prob": 0.3,
          "op_family": "full",
          "query_family": "all",
          "slot_capacity": 7,
          "init_mode": "oracle",
          "transition_mode": "primitive_router",
          "supervision": "full_belief",
          "slot_dim": 64,
          "hidden_dim": 128,
          "fourier_order": 8,
          "train_steps": 500,
          "length": 2,
          "query_type": "A",
          "k": 3,
          "n": 128,
          "decoder_query_target_mass": 0.9999849796295166,
          "decoder_query_target_nll": 1.2342402935028076,
          "decoder_query_top1_on_support": 1.0,
          "mean_decoder_query_support_size": 4.3203125,
          "decoder_belief_target_mass": 0.9999264478683472,
          "decoder_belief_target_nll": 1.456474781036377,
          "decoder_belief_top1_on_support": 1.0,
          "mean_decoder_belief_support_size": 4.953125,
          "init_belief_target_mass": 0.9999985694885254,
          "init_belief_target_nll": 1.9459115266799927,
          "init_belief_top1_on_support": 1.0,
          "init_slot_relation_accuracy": 1.0,
          "init_slot_unique_a_frac": 1.0,
          "init_mixture_a_entropy": 1.945910096168518,
          "init_mixture_b_entropy": 1.945910096168518,
          "init_slot_a_overlap": 2.2507009589389781e-07,
          "init_slot_b_overlap": 2.2507009589389781e-07,
          "mean_slot_purity": 0.8536256551742554,
          "mean_slot_entropy": 0.2611013650894165,
          "mean_weight_entropy": 1.4564307928085327,
          "mean_route_entropy": -1.0,
          "mean_route_accuracy": -1.0,
          "mean_target_support_size": 4.953125
        },
        {
          "model": "end_to_end_structured_slot_executor",
          "variant": "smoke_oracle_primitive_router",
          "modulus": 7,
          "observe_mod": 3,
          "observe_prob": 0.3,
          "op_family": "full",
          "query_family": "all",
          "slot_capacity": 7,
          "init_mode": "oracle",
          "transition_mode": "primitive_router",
          "supervision": "full_belief",
          "slot_dim": 64,
          "hidden_dim": 128,
          "fourier_order": 8,
          "train_steps": 500,
          "length": 2,
          "query_type": "B",
          "k": 0,
          "n": 128,
          "decoder_query_target_mass": 0.6383928060531616,
          "decoder_query_target_nll": 1.9459102153778076,
          "decoder_query_top1_on_support": 0.6484375,
          "mean_decoder_query_support_size": 4.46875,
          "decoder_belief_target_mass": 0.17410700023174286,
          "decoder_belief_target_nll": 13.354869842529297,
          "decoder_belief_top1_on_support": 0.234375,
          "mean_decoder_belief_support_size": 4.9921875,
          "init_belief_target_mass": 0.9999985694885254,
          "init_belief_target_nll": 1.9459115266799927,
          "init_belief_top1_on_support": 1.0,
          "init_slot_relation_accuracy": 1.0,
          "init_slot_unique_a_frac": 1.0,
          "init_mixture_a_entropy": 1.945910096168518,
          "init_mixture_b_entropy": 1.945910096168518,
          "init_slot_a_overlap": 2.2507009589389781e-07,
          "init_slot_b_overlap": 2.2507009589389781e-07,
          "mean_slot_purity": 0.9999986290931702,
          "mean_slot_entropy": 2.3037249775370583e-05,
          "mean_weight_entropy": 1.9459102153778076,
          "mean_route_entropy": -1.0,
          "mean_route_accuracy": -1.0,
          "mean_target_support_size": 4.9921875
        },
        {
          "model": "end_to_end_structured_slot_executor",
          "variant": "smoke_oracle_primitive_router",
          "modulus": 7,
          "observe_mod": 3,
          "observe_prob": 0.3,
          "op_family": "full",
          "query_family": "all",
          "slot_capacity": 7,
          "init_mode": "oracle",
          "transition_mode": "primitive_router",
          "supervision": "full_belief",
          "slot_dim": 64,
          "hidden_dim": 128,
          "fourier_order": 8,
          "train_steps": 500,
          "length": 2,
          "query_type": "B",
          "k": 1,
          "n": 128,
          "decoder_query_target_mass": 0.7604141235351562,
          "decoder_query_target_nll": 3.3505325317382812,
          "decoder_query_top1_on_support": 0.796875,
          "mean_decoder_query_support_size": 4.46875,
          "decoder_belief_target_mass": 0.2695273458957672,
          "decoder_belief_target_nll": 10.133505821228027,
          "decoder_belief_top1_on_support": 0.3671875,
          "mean_decoder_belief_support_size": 4.9921875,
          "init_belief_target_mass": 0.9999985694885254,
          "init_belief_target_nll": 1.9459115266799927,
          "init_belief_top1_on_support": 1.0,
          "init_slot_relation_accuracy": 1.0,
          "init_slot_unique_a_frac": 1.0,
          "init_mixture_a_entropy": 1.945910096168518,
          "init_mixture_b_entropy": 1.945910096168518,
          "init_slot_a_overlap": 2.2507009589389781e-07,
          "init_slot_b_overlap": 2.2507009589389781e-07,
          "mean_slot_purity": 0.8939379453659058,
          "mean_slot_entropy": 0.15914824604988098,
          "mean_weight_entropy": 1.6313012838363647,
          "mean_route_entropy": 0.0004632804193533957,
          "mean_route_accuracy": 1.0,
          "mean_target_support_size": 4.9921875
        },
        {
          "model": "end_to_end_structured_slot_executor",
          "variant": "smoke_oracle_primitive_router",
          "modulus": 7,
          "observe_mod": 3,
          "observe_prob": 0.3,
          "op_family": "full",
          "query_family": "all",
          "slot_capacity": 7,
          "init_mode": "oracle",
          "transition_mode": "primitive_router",
          "supervision": "full_belief",
          "slot_dim": 64,
          "hidden_dim": 128,
          "fourier_order": 8,
          "train_steps": 500,
          "length": 2,
          "query_type": "B",
          "k": 2,
          "n": 128,
          "decoder_query_target_mass": 0.9999813437461853,
          "decoder_query_target_nll": 1.2724725008010864,
          "decoder_query_top1_on_support": 1.0,
          "mean_decoder_query_support_size": 4.46875,
          "decoder_belief_target_mass": 0.999923825263977,
          "decoder_belief_target_nll": 1.460213303565979,
          "decoder_belief_top1_on_support": 1.0,
          "mean_decoder_belief_support_size": 4.9921875,
          "init_belief_target_mass": 0.9999985694885254,
          "init_belief_target_nll": 1.9459115266799927,
          "init_belief_top1_on_support": 1.0,
          "init_slot_relation_accuracy": 1.0,
          "init_slot_unique_a_frac": 1.0,
          "init_mixture_a_entropy": 1.945910096168518,
          "init_mixture_b_entropy": 1.945910096168518,
          "init_slot_a_overlap": 2.2507009589389781e-07,
          "init_slot_b_overlap": 2.2507009589389781e-07,
          "mean_slot_purity": 0.8603193163871765,
          "mean_slot_entropy": 0.23273232579231262,
          "mean_weight_entropy": 1.4601614475250244,
          "mean_route_entropy": 0.0005148337222635746,
          "mean_route_accuracy": 1.0,
          "mean_target_support_size": 4.9921875
        },
        {
          "model": "end_to_end_structured_slot_executor",
          "variant": "smoke_oracle_primitive_router",
          "modulus": 7,
          "observe_mod": 3,
          "observe_prob": 0.3,
          "op_family": "full",
          "query_family": "all",
          "slot_capacity": 7,
          "init_mode": "oracle",
          "transition_mode": "primitive_router",
          "supervision": "full_belief",
          "slot_dim": 64,
          "hidden_dim": 128,
          "fourier_order": 8,
          "train_steps": 500,
          "length": 2,
          "query_type": "B",
          "k": 3,
          "n": 128,
          "decoder_query_target_mass": 0.9999813437461853,
          "decoder_query_target_nll": 1.2724725008010864,
          "decoder_query_top1_on_support": 1.0,
          "mean_decoder_query_support_size": 4.46875,
          "decoder_belief_target_mass": 0.999923825263977,
          "decoder_belief_target_nll": 1.460213303565979,
          "decoder_belief_top1_on_support": 1.0,
          "mean_decoder_belief_support_size": 4.9921875,
          "init_belief_target_mass": 0.9999985694885254,
          "init_belief_target_nll": 1.9459115266799927,
          "init_belief_top1_on_support": 1.0,
          "init_slot_relation_accuracy": 1.0,
          "init_slot_unique_a_frac": 1.0,
          "init_mixture_a_entropy": 1.945910096168518,
          "init_mixture_b_entropy": 1.945910096168518,
          "init_slot_a_overlap": 2.2507009589389781e-07,
          "init_slot_b_overlap": 2.2507009589389781e-07,
          "mean_slot_purity": 0.8603193163871765,
          "mean_slot_entropy": 0.23273232579231262,
          "mean_weight_entropy": 1.4601614475250244,
          "mean_route_entropy": -1.0,
          "mean_route_accuracy": -1.0,
          "mean_target_support_size": 4.9921875
        },
        {
          "model": "end_to_end_structured_slot_executor",
          "variant": "smoke_oracle_primitive_router",
          "modulus": 7,
          "observe_mod": 3,
          "observe_prob": 0.3,
          "op_family": "full",
          "query_family": "all",
          "slot_capacity": 7,
          "init_mode": "oracle",
          "transition_mode": "primitive_router",
          "supervision": "full_belief",
          "slot_dim": 64,
          "hidden_dim": 128,
          "fourier_order": 8,
          "train_steps": 500,
          "length": 2,
          "query_type": "A_PLUS_B",
          "k": 0,
          "n": 128,
          "decoder_query_target_mass": 0.6350445747375488,
          "decoder_query_target_nll": 1.9459102153778076,
          "decoder_query_top1_on_support": 0.671875,
          "mean_decoder_query_support_size": 4.4453125,
          "decoder_belief_target_mass": 0.11272317171096802,
          "decoder_belief_target_nll": 14.320089340209961,
          "decoder_belief_top1_on_support": 0.1796875,
          "mean_decoder_belief_support_size": 4.5859375,
          "init_belief_target_mass": 0.9999985694885254,
          "init_belief_target_nll": 1.9459115266799927,
          "init_belief_top1_on_support": 1.0,
          "init_slot_relation_accuracy": 1.0,
          "init_slot_unique_a_frac": 1.0,
          "init_mixture_a_entropy": 1.945910096168518,
          "init_mixture_b_entropy": 1.945910096168518,
          "init_slot_a_overlap": 2.2507009589389781e-07,
          "init_slot_b_overlap": 2.2507009589389781e-07,
          "mean_slot_purity": 0.9999986290931702,
          "mean_slot_entropy": 2.3037249775370583e-05,
          "mean_weight_entropy": 1.9459102153778076,
          "mean_route_entropy": -1.0,
          "mean_route_accuracy": -1.0,
          "mean_target_support_size": 4.5859375
        },
        {
          "model": "end_to_end_structured_slot_executor",
          "variant": "smoke_oracle_primitive_router",
          "modulus": 7,
          "observe_mod": 3,
          "observe_prob": 0.3,
          "op_family": "full",
          "query_family": "all",
          "slot_capacity": 7,
          "init_mode": "oracle",
          "transition_mode": "primitive_router",
          "supervision": "full_belief",
          "slot_dim": 64,
          "hidden_dim": 128,
          "fourier_order": 8,
          "train_steps": 500,
          "length": 2,
          "query_type": "A_PLUS_B",
          "k": 1,
          "n": 128,
          "decoder_query_target_mass": 0.6718732118606567,
          "decoder_query_target_nll": 3.639523983001709,
          "decoder_query_top1_on_support": 0.6953125,
          "mean_decoder_query_support_size": 4.4453125,
          "decoder_belief_target_mass": 0.2762206792831421,
          "decoder_belief_target_nll": 9.51441764831543,
          "decoder_belief_top1_on_support": 0.3046875,
          "mean_decoder_belief_support_size": 4.5859375,
          "init_belief_target_mass": 0.9999985694885254,
          "init_belief_target_nll": 1.9459115266799927,
          "init_belief_top1_on_support": 1.0,
          "init_slot_relation_accuracy": 1.0,
          "init_slot_unique_a_frac": 1.0,
          "init_mixture_a_entropy": 1.945910096168518,
          "init_mixture_b_entropy": 1.945910096168518,
          "init_slot_a_overlap": 2.2507009589389781e-07,
          "init_slot_b_overlap": 2.2507009589389781e-07,
          "mean_slot_purity": 0.8825914859771729,
          "mean_slot_entropy": 0.1756579428911209,
          "mean_weight_entropy": 1.595320463180542,
          "mean_route_entropy": 0.0004810536920558661,
          "mean_route_accuracy": 1.0,
          "mean_target_support_size": 4.5859375
        },
        {
          "model": "end_to_end_structured_slot_executor",
          "variant": "smoke_oracle_primitive_router",
          "modulus": 7,
          "observe_mod": 3,
          "observe_prob": 0.3,
          "op_family": "full",
          "query_family": "all",
          "slot_capacity": 7,
          "init_mode": "oracle",
          "transition_mode": "primitive_router",
          "supervision": "full_belief",
          "slot_dim": 64,
          "hidden_dim": 128,
          "fourier_order": 8,
          "train_steps": 500,
          "length": 2,
          "query_type": "A_PLUS_B",
          "k": 2,
          "n": 128,
          "decoder_query_target_mass": 0.9999686479568481,
          "decoder_query_target_nll": 1.3119099140167236,
          "decoder_query_top1_on_support": 1.0,
          "mean_decoder_query_support_size": 4.4453125,
          "decoder_belief_target_mass": 0.9999217391014099,
          "decoder_belief_target_nll": 1.3575642108917236,
          "decoder_belief_top1_on_support": 1.0,
          "mean_decoder_belief_support_size": 4.5859375,
          "init_belief_target_mass": 0.9999985694885254,
          "init_belief_target_nll": 1.9459115266799927,
          "init_belief_top1_on_support": 1.0,
          "init_slot_relation_accuracy": 1.0,
          "init_slot_unique_a_frac": 1.0,
          "init_mixture_a_entropy": 1.945910096168518,
          "init_mixture_b_entropy": 1.945910096168518,
          "init_slot_a_overlap": 2.2507009589389781e-07,
          "init_slot_b_overlap": 2.2507009589389781e-07,
          "mean_slot_purity": 0.8376087546348572,
          "mean_slot_entropy": 0.27931272983551025,
          "mean_weight_entropy": 1.3575246334075928,
          "mean_route_entropy": 0.0005122432485222816,
          "mean_route_accuracy": 1.0,
          "mean_target_support_size": 4.5859375
        },
        {
          "model": "end_to_end_structured_slot_executor",
          "variant": "smoke_oracle_primitive_router",
          "modulus": 7,
          "observe_mod": 3,
          "observe_prob": 0.3,
          "op_family": "full",
          "query_family": "all",
          "slot_capacity": 7,
          "init_mode": "oracle",
          "transition_mode": "primitive_router",
          "supervision": "full_belief",
          "slot_dim": 64,
          "hidden_dim": 128,
          "fourier_order": 8,
          "train_steps": 500,
          "length": 2,
          "query_type": "A_PLUS_B",
          "k": 3,
          "n": 128,
          "decoder_query_target_mass": 0.9999686479568481,
          "decoder_query_target_nll": 1.3119099140167236,
          "decoder_query_top1_on_support": 1.0,
          "mean_decoder_query_support_size": 4.4453125,
          "decoder_belief_target_mass": 0.9999217391014099,
          "decoder_belief_target_nll": 1.3575642108917236,
          "decoder_belief_top1_on_support": 1.0,
          "mean_decoder_belief_support_size": 4.5859375,
          "init_belief_target_mass": 0.9999985694885254,
          "init_belief_target_nll": 1.9459115266799927,
          "init_belief_top1_on_support": 1.0,
          "init_slot_relation_accuracy": 1.0,
          "init_slot_unique_a_frac": 1.0,
          "init_mixture_a_entropy": 1.945910096168518,
          "init_mixture_b_entropy": 1.945910096168518,
          "init_slot_a_overlap": 2.2507009589389781e-07,
          "init_slot_b_overlap": 2.2507009589389781e-07,
          "mean_slot_purity": 0.8376087546348572,
          "mean_slot_entropy": 0.27931272983551025,
          "mean_weight_entropy": 1.3575246334075928,
          "mean_route_entropy": -1.0,
          "mean_route_accuracy": -1.0,
          "mean_target_support_size": 4.5859375
        },
        {
          "model": "end_to_end_structured_slot_executor",
          "variant": "smoke_oracle_primitive_router",
          "modulus": 7,
          "observe_mod": 3,
          "observe_prob": 0.3,
          "op_family": "full",
          "query_family": "all",
          "slot_capacity": 7,
          "init_mode": "oracle",
          "transition_mode": "primitive_router",
          "supervision": "full_belief",
          "slot_dim": 64,
          "hidden_dim": 128,
          "fourier_order": 8,
          "train_steps": 500,
          "length": 2,
          "query_type": "A_MINUS_B",
          "k": 0,
          "n": 128,
          "decoder_query_target_mass": 0.5703123807907104,
          "decoder_query_target_nll": 11.99549388885498,
          "decoder_query_top1_on_support": 0.5703125,
          "mean_decoder_query_support_size": 3.4453125,
          "decoder_belief_target_mass": 0.14174097776412964,
          "decoder_belief_target_nll": 13.941405296325684,
          "decoder_belief_top1_on_support": 0.2421875,
          "mean_decoder_belief_support_size": 4.7734375,
          "init_belief_target_mass": 0.9999985694885254,
          "init_belief_target_nll": 1.9459115266799927,
          "init_belief_top1_on_support": 1.0,
          "init_slot_relation_accuracy": 1.0,
          "init_slot_unique_a_frac": 1.0,
          "init_mixture_a_entropy": 1.945910096168518,
          "init_mixture_b_entropy": 1.945910096168518,
          "init_slot_a_overlap": 2.2507009589389781e-07,
          "init_slot_b_overlap": 2.2507009589389781e-07,
          "mean_slot_purity": 0.9999986290931702,
          "mean_slot_entropy": 2.3037249775370583e-05,
          "mean_weight_entropy": 1.9459102153778076,
          "mean_route_entropy": -1.0,
          "mean_route_accuracy": -1.0,
          "mean_target_support_size": 4.7734375
        },
        {
          "model": "end_to_end_structured_slot_executor",
          "variant": "smoke_oracle_primitive_router",
          "modulus": 7,
          "observe_mod": 3,
          "observe_prob": 0.3,
          "op_family": "full",
          "query_family": "all",
          "slot_capacity": 7,
          "init_mode": "oracle",
          "transition_mode": "primitive_router",
          "supervision": "full_belief",
          "slot_dim": 64,
          "hidden_dim": 128,
          "fourier_order": 8,
          "train_steps": 500,
          "length": 2,
          "query_type": "A_MINUS_B",
          "k": 1,
          "n": 128,
          "decoder_query_target_mass": 0.6607059240341187,
          "decoder_query_target_nll": 6.075117111206055,
          "decoder_query_top1_on_support": 0.6796875,
          "mean_decoder_query_support_size": 3.4453125,
          "decoder_belief_target_mass": 0.2922188937664032,
          "decoder_belief_target_nll": 9.520132064819336,
          "decoder_belief_top1_on_support": 0.328125,
          "mean_decoder_belief_support_size": 4.7734375,
          "init_belief_target_mass": 0.9999985694885254,
          "init_belief_target_nll": 1.9459115266799927,
          "init_belief_top1_on_support": 1.0,
          "init_slot_relation_accuracy": 1.0,
          "init_slot_unique_a_frac": 1.0,
          "init_mixture_a_entropy": 1.945910096168518,
          "init_mixture_b_entropy": 1.945910096168518,
          "init_slot_a_overlap": 2.2507009589389781e-07,
          "init_slot_b_overlap": 2.2507009589389781e-07,
          "mean_slot_purity": 0.8937507271766663,
          "mean_slot_entropy": 0.16020144522190094,
          "mean_weight_entropy": 1.634468913078308,
          "mean_route_entropy": 0.00048591659287922084,
          "mean_route_accuracy": 1.0,
          "mean_target_support_size": 4.7734375
        },
        {
          "model": "end_to_end_structured_slot_executor",
          "variant": "smoke_oracle_primitive_router",
          "modulus": 7,
          "observe_mod": 3,
          "observe_prob": 0.3,
          "op_family": "full",
          "query_family": "all",
          "slot_capacity": 7,
          "init_mode": "oracle",
          "transition_mode": "primitive_router",
          "supervision": "full_belief",
          "slot_dim": 64,
          "hidden_dim": 128,
          "fourier_order": 8,
          "train_steps": 500,
          "length": 2,
          "query_type": "A_MINUS_B",
          "k": 2,
          "n": 128,
          "decoder_query_target_mass": 0.9999544024467468,
          "decoder_query_target_nll": 0.8539047241210938,
          "decoder_query_top1_on_support": 1.0,
          "mean_decoder_query_support_size": 3.4453125,
          "decoder_belief_target_mass": 0.9999212026596069,
          "decoder_belief_target_nll": 1.4100755453109741,
          "decoder_belief_top1_on_support": 1.0,
          "mean_decoder_belief_support_size": 4.7734375,
          "init_belief_target_mass": 0.9999985694885254,
          "init_belief_target_nll": 1.9459115266799927,
          "init_belief_top1_on_support": 1.0,
          "init_slot_relation_accuracy": 1.0,
          "init_slot_unique_a_frac": 1.0,
          "init_mixture_a_entropy": 1.945910096168518,
          "init_mixture_b_entropy": 1.945910096168518,
          "init_slot_a_overlap": 2.2507009589389781e-07,
          "init_slot_b_overlap": 2.2507009589389781e-07,
          "mean_slot_purity": 0.8506555557250977,
          "mean_slot_entropy": 0.2540473937988281,
          "mean_weight_entropy": 1.4100364446640015,
          "mean_route_entropy": 0.0005349356215447187,
          "mean_route_accuracy": 1.0,
          "mean_target_support_size": 4.7734375
        },
        {
          "model": "end_to_end_structured_slot_executor",
          "variant": "smoke_oracle_primitive_router",
          "modulus": 7,
          "observe_mod": 3,
          "observe_prob": 0.3,
          "op_family": "full",
          "query_family": "all",
          "slot_capacity": 7,
          "init_mode": "oracle",
          "transition_mode": "primitive_router",
          "supervision": "full_belief",
          "slot_dim": 64,
          "hidden_dim": 128,
          "fourier_order": 8,
          "train_steps": 500,
          "length": 2,
          "query_type": "A_MINUS_B",
          "k": 3,
          "n": 128,
          "decoder_query_target_mass": 0.9999544024467468,
          "decoder_query_target_nll": 0.8539047241210938,
          "decoder_query_top1_on_support": 1.0,
          "mean_decoder_query_support_size": 3.4453125,
          "decoder_belief_target_mass": 0.9999212026596069,
          "decoder_belief_target_nll": 1.4100755453109741,
          "decoder_belief_top1_on_support": 1.0,
          "mean_decoder_belief_support_size": 4.7734375,
          "init_belief_target_mass": 0.9999985694885254,
          "init_belief_target_nll": 1.9459115266799927,
          "init_belief_top1_on_support": 1.0,
          "init_slot_relation_accuracy": 1.0,
          "init_slot_unique_a_frac": 1.0,
          "init_mixture_a_entropy": 1.945910096168518,
          "init_mixture_b_entropy": 1.945910096168518,
          "init_slot_a_overlap": 2.2507009589389781e-07,
          "init_slot_b_overlap": 2.2507009589389781e-07,
          "mean_slot_purity": 0.8506555557250977,
          "mean_slot_entropy": 0.2540473937988281,
          "mean_weight_entropy": 1.4100364446640015,
          "mean_route_entropy": -1.0,
          "mean_route_accuracy": -1.0,
          "mean_target_support_size": 4.7734375
        },
        {
          "model": "end_to_end_structured_slot_executor",
          "variant": "smoke_oracle_primitive_router",
          "modulus": 7,
          "observe_mod": 3,
          "observe_prob": 0.3,
          "op_family": "full",
          "query_family": "all",
          "slot_capacity": 7,
          "init_mode": "oracle",
          "transition_mode": "primitive_router",
          "supervision": "full_belief",
          "slot_dim": 64,
          "hidden_dim": 128,
          "fourier_order": 8,
          "train_steps": 500,
          "length": 3,
          "query_type": "A",
          "k": 0,
          "n": 128,
          "decoder_query_target_mass": 0.5491070747375488,
          "decoder_query_target_nll": 1.9459102153778076,
          "decoder_query_top1_on_support": 0.4765625,
          "mean_decoder_query_support_size": 3.84375,
          "decoder_belief_target_mass": 0.10491067916154861,
          "decoder_belief_target_nll": 14.51655101776123,
          "decoder_belief_top1_on_support": 0.1796875,
          "mean_decoder_belief_support_size": 4.328125,
          "init_belief_target_mass": 0.9999985694885254,
          "init_belief_target_nll": 1.9459115266799927,
          "init_belief_top1_on_support": 1.0,
          "init_slot_relation_accuracy": 1.0,
          "init_slot_unique_a_frac": 1.0,
          "init_mixture_a_entropy": 1.945910096168518,
          "init_mixture_b_entropy": 1.945910096168518,
          "init_slot_a_overlap": 2.2507009589389781e-07,
          "init_slot_b_overlap": 2.2507009589389781e-07,
          "mean_slot_purity": 0.9999986290931702,
          "mean_slot_entropy": 2.3037249775370583e-05,
          "mean_weight_entropy": 1.9459102153778076,
          "mean_route_entropy": -1.0,
          "mean_route_accuracy": -1.0,
          "mean_target_support_size": 4.328125
        },
        {
          "model": "end_to_end_structured_slot_executor",
          "variant": "smoke_oracle_primitive_router",
          "modulus": 7,
          "observe_mod": 3,
          "observe_prob": 0.3,
          "op_family": "full",
          "query_family": "all",
          "slot_capacity": 7,
          "init_mode": "oracle",
          "transition_mode": "primitive_router",
          "supervision": "full_belief",
          "slot_dim": 64,
          "hidden_dim": 128,
          "fourier_order": 8,
          "train_steps": 500,
          "length": 3,
          "query_type": "A",
          "k": 1,
          "n": 128,
          "decoder_query_target_mass": 0.5879824161529541,
          "decoder_query_target_nll": 3.8487658500671387,
          "decoder_query_top1_on_support": 0.5703125,
          "mean_decoder_query_support_size": 3.84375,
          "decoder_belief_target_mass": 0.19345161318778992,
          "decoder_belief_target_nll": 11.889602661132812,
          "decoder_belief_top1_on_support": 0.203125,
          "mean_decoder_belief_support_size": 4.328125,
          "init_belief_target_mass": 0.9999985694885254,
          "init_belief_target_nll": 1.9459115266799927,
          "init_belief_top1_on_support": 1.0,
          "init_slot_relation_accuracy": 1.0,
          "init_slot_unique_a_frac": 1.0,
          "init_mixture_a_entropy": 1.945910096168518,
          "init_mixture_b_entropy": 1.945910096168518,
          "init_slot_a_overlap": 2.2507009589389781e-07,
          "init_slot_b_overlap": 2.2507009589389781e-07,
          "mean_slot_purity": 0.9289047718048096,
          "mean_slot_entropy": 0.10445550084114075,
          "mean_weight_entropy": 1.7234054803848267,
          "mean_route_entropy": 0.00044884742237627506,
          "mean_route_accuracy": 1.0,
          "mean_target_support_size": 4.328125
        },
        {
          "model": "end_to_end_structured_slot_executor",
          "variant": "smoke_oracle_primitive_router",
          "modulus": 7,
          "observe_mod": 3,
          "observe_prob": 0.3,
          "op_family": "full",
          "query_family": "all",
          "slot_capacity": 7,
          "init_mode": "oracle",
          "transition_mode": "primitive_router",
          "supervision": "full_belief",
          "slot_dim": 64,
          "hidden_dim": 128,
          "fourier_order": 8,
          "train_steps": 500,
          "length": 3,
          "query_type": "A",
          "k": 2,
          "n": 128,
          "decoder_query_target_mass": 0.722835123538971,
          "decoder_query_target_nll": 3.453063488006592,
          "decoder_query_top1_on_support": 0.703125,
          "mean_decoder_query_support_size": 3.84375,
          "decoder_belief_target_mass": 0.32327574491500854,
          "decoder_belief_target_nll": 8.608396530151367,
          "decoder_belief_top1_on_support": 0.3984375,
          "mean_decoder_belief_support_size": 4.328125,
          "init_belief_target_mass": 0.9999985694885254,
          "init_belief_target_nll": 1.9459115266799927,
          "init_belief_top1_on_support": 1.0,
          "init_slot_relation_accuracy": 1.0,
          "init_slot_unique_a_frac": 1.0,
          "init_mixture_a_entropy": 1.945910096168518,
          "init_mixture_b_entropy": 1.945910096168518,
          "init_slot_a_overlap": 2.2507009589389781e-07,
          "init_slot_b_overlap": 2.2507009589389781e-07,
          "mean_slot_purity": 0.892731249332428,
          "mean_slot_entropy": 0.18288323283195496,
          "mean_weight_entropy": 1.4837703704833984,
          "mean_route_entropy": 0.0005364084499888122,
          "mean_route_accuracy": 1.0,
          "mean_target_support_size": 4.328125
        },
        {
          "model": "end_to_end_structured_slot_executor",
          "variant": "smoke_oracle_primitive_router",
          "modulus": 7,
          "observe_mod": 3,
          "observe_prob": 0.3,
          "op_family": "full",
          "query_family": "all",
          "slot_capacity": 7,
          "init_mode": "oracle",
          "transition_mode": "primitive_router",
          "supervision": "full_belief",
          "slot_dim": 64,
          "hidden_dim": 128,
          "fourier_order": 8,
          "train_steps": 500,
          "length": 3,
          "query_type": "A",
          "k": 3,
          "n": 128,
          "decoder_query_target_mass": 0.9999691843986511,
          "decoder_query_target_nll": 1.0970442295074463,
          "decoder_query_top1_on_support": 1.0,
          "mean_decoder_query_support_size": 3.84375,
          "decoder_belief_target_mass": 0.9998762607574463,
          "decoder_belief_target_nll": 1.2727856636047363,
          "decoder_belief_top1_on_support": 1.0,
          "mean_decoder_belief_support_size": 4.328125,
          "init_belief_target_mass": 0.9999985694885254,
          "init_belief_target_nll": 1.9459115266799927,
          "init_belief_top1_on_support": 1.0,
          "init_slot_relation_accuracy": 1.0,
          "init_slot_unique_a_frac": 1.0,
          "init_mixture_a_entropy": 1.945910096168518,
          "init_mixture_b_entropy": 1.945910096168518,
          "init_slot_a_overlap": 2.2507009589389781e-07,
          "init_slot_b_overlap": 2.2507009589389781e-07,
          "mean_slot_purity": 0.8562296628952026,
          "mean_slot_entropy": 0.27680885791778564,
          "mean_weight_entropy": 1.2727727890014648,
          "mean_route_entropy": 0.0005032228073105216,
          "mean_route_accuracy": 1.0,
          "mean_target_support_size": 4.328125
        },
        {
          "model": "end_to_end_structured_slot_executor",
          "variant": "smoke_oracle_primitive_router",
          "modulus": 7,
          "observe_mod": 3,
          "observe_prob": 0.3,
          "op_family": "full",
          "query_family": "all",
          "slot_capacity": 7,
          "init_mode": "oracle",
          "transition_mode": "primitive_router",
          "supervision": "full_belief",
          "slot_dim": 64,
          "hidden_dim": 128,
          "fourier_order": 8,
          "train_steps": 500,
          "length": 3,
          "query_type": "B",
          "k": 0,
          "n": 128,
          "decoder_query_target_mass": 0.5111607313156128,
          "decoder_query_target_nll": 1.9459102153778076,
          "decoder_query_top1_on_support": 0.5,
          "mean_decoder_query_support_size": 3.578125,
          "decoder_belief_target_mass": 0.09486603736877441,
          "decoder_belief_target_nll": 14.715858459472656,
          "decoder_belief_top1_on_support": 0.09375,
          "mean_decoder_belief_support_size": 4.09375,
          "init_belief_target_mass": 0.9999985694885254,
          "init_belief_target_nll": 1.9459115266799927,
          "init_belief_top1_on_support": 1.0,
          "init_slot_relation_accuracy": 1.0,
          "init_slot_unique_a_frac": 1.0,
          "init_mixture_a_entropy": 1.945910096168518,
          "init_mixture_b_entropy": 1.945910096168518,
          "init_slot_a_overlap": 2.2507009589389781e-07,
          "init_slot_b_overlap": 2.2507009589389781e-07,
          "mean_slot_purity": 0.9999986290931702,
          "mean_slot_entropy": 2.3037249775370583e-05,
          "mean_weight_entropy": 1.9459102153778076,
          "mean_route_entropy": -1.0,
          "mean_route_accuracy": -1.0,
          "mean_target_support_size": 4.09375
        },
        {
          "model": "end_to_end_structured_slot_executor",
          "variant": "smoke_oracle_primitive_router",
          "modulus": 7,
          "observe_mod": 3,
          "observe_prob": 0.3,
          "op_family": "full",
          "query_family": "all",
          "slot_capacity": 7,
          "init_mode": "oracle",
          "transition_mode": "primitive_router",
          "supervision": "full_belief",
          "slot_dim": 64,
          "hidden_dim": 128,
          "fourier_order": 8,
          "train_steps": 500,
          "length": 3,
          "query_type": "B",
          "k": 1,
          "n": 128,
          "decoder_query_target_mass": 0.5704962015151978,
          "decoder_query_target_nll": 4.388654708862305,
          "decoder_query_top1_on_support": 0.5390625,
          "mean_decoder_query_support_size": 3.578125,
          "decoder_belief_target_mass": 0.16740602254867554,
          "decoder_belief_target_nll": 12.525132179260254,
          "decoder_belief_top1_on_support": 0.109375,
          "mean_decoder_belief_support_size": 4.09375,
          "init_belief_target_mass": 0.9999985694885254,
          "init_belief_target_nll": 1.9459115266799927,
          "init_belief_top1_on_support": 1.0,
          "init_slot_relation_accuracy": 1.0,
          "init_slot_unique_a_frac": 1.0,
          "init_mixture_a_entropy": 1.945910096168518,
          "init_mixture_b_entropy": 1.945910096168518,
          "init_slot_a_overlap": 2.2507009589389781e-07,
          "init_slot_b_overlap": 2.2507009589389781e-07,
          "mean_slot_purity": 0.9063990116119385,
          "mean_slot_entropy": 0.1364324986934662,
          "mean_weight_entropy": 1.6482760906219482,
          "mean_route_entropy": 0.00046032556565478444,
          "mean_route_accuracy": 1.0,
          "mean_target_support_size": 4.09375
        },
        {
          "model": "end_to_end_structured_slot_executor",
          "variant": "smoke_oracle_primitive_router",
          "modulus": 7,
          "observe_mod": 3,
          "observe_prob": 0.3,
          "op_family": "full",
          "query_family": "all",
          "slot_capacity": 7,
          "init_mode": "oracle",
          "transition_mode": "primitive_router",
          "supervision": "full_belief",
          "slot_dim": 64,
          "hidden_dim": 128,
          "fourier_order": 8,
          "train_steps": 500,
          "length": 3,
          "query_type": "B",
          "k": 2,
          "n": 128,
          "decoder_query_target_mass": 0.717994749546051,
          "decoder_query_target_nll": 3.460594654083252,
          "decoder_query_top1_on_support": 0.7265625,
          "mean_decoder_query_support_size": 3.578125,
          "decoder_belief_target_mass": 0.2620801627635956,
          "decoder_belief_target_nll": 9.57794189453125,
          "decoder_belief_top1_on_support": 0.28125,
          "mean_decoder_belief_support_size": 4.09375,
          "init_belief_target_mass": 0.9999985694885254,
          "init_belief_target_nll": 1.9459115266799927,
          "init_belief_top1_on_support": 1.0,
          "init_slot_relation_accuracy": 1.0,
          "init_slot_unique_a_frac": 1.0,
          "init_mixture_a_entropy": 1.945910096168518,
          "init_mixture_b_entropy": 1.945910096168518,
          "init_slot_a_overlap": 2.2507009589389781e-07,
          "init_slot_b_overlap": 2.2507009589389781e-07,
          "mean_slot_purity": 0.8609458208084106,
          "mean_slot_entropy": 0.22986114025115967,
          "mean_weight_entropy": 1.3887946605682373,
          "mean_route_entropy": 0.0004578001389745623,
          "mean_route_accuracy": 1.0,
          "mean_target_support_size": 4.09375
        },
        {
          "model": "end_to_end_structured_slot_executor",
          "variant": "smoke_oracle_primitive_router",
          "modulus": 7,
          "observe_mod": 3,
          "observe_prob": 0.3,
          "op_family": "full",
          "query_family": "all",
          "slot_capacity": 7,
          "init_mode": "oracle",
          "transition_mode": "primitive_router",
          "supervision": "full_belief",
          "slot_dim": 64,
          "hidden_dim": 128,
          "fourier_order": 8,
          "train_steps": 500,
          "length": 3,
          "query_type": "B",
          "k": 3,
          "n": 128,
          "decoder_query_target_mass": 0.9999610185623169,
          "decoder_query_target_nll": 1.0400084257125854,
          "decoder_query_top1_on_support": 1.0,
          "mean_decoder_query_support_size": 3.578125,
          "decoder_belief_target_mass": 0.9998733997344971,
          "decoder_belief_target_nll": 1.2329102754592896,
          "decoder_belief_top1_on_support": 1.0,
          "mean_decoder_belief_support_size": 4.09375,
          "init_belief_target_mass": 0.9999985694885254,
          "init_belief_target_nll": 1.9459115266799927,
          "init_belief_top1_on_support": 1.0,
          "init_slot_relation_accuracy": 1.0,
          "init_slot_unique_a_frac": 1.0,
          "init_mixture_a_entropy": 1.945910096168518,
          "init_mixture_b_entropy": 1.945910096168518,
          "init_slot_a_overlap": 2.2507009589389781e-07,
          "init_slot_b_overlap": 2.2507009589389781e-07,
          "mean_slot_purity": 0.827470600605011,
          "mean_slot_entropy": 0.31960880756378174,
          "mean_weight_entropy": 1.2328853607177734,
          "mean_route_entropy": 0.0004822189803235233,
          "mean_route_accuracy": 1.0,
          "mean_target_support_size": 4.09375
        },
        {
          "model": "end_to_end_structured_slot_executor",
          "variant": "smoke_oracle_primitive_router",
          "modulus": 7,
          "observe_mod": 3,
          "observe_prob": 0.3,
          "op_family": "full",
          "query_family": "all",
          "slot_capacity": 7,
          "init_mode": "oracle",
          "transition_mode": "primitive_router",
          "supervision": "full_belief",
          "slot_dim": 64,
          "hidden_dim": 128,
          "fourier_order": 8,
          "train_steps": 500,
          "length": 3,
          "query_type": "A_PLUS_B",
          "k": 0,
          "n": 128,
          "decoder_query_target_mass": 0.5122767686843872,
          "decoder_query_target_nll": 1.9459102153778076,
          "decoder_query_top1_on_support": 0.5390625,
          "mean_decoder_query_support_size": 3.5859375,
          "decoder_belief_target_mass": 0.0792410597205162,
          "decoder_belief_target_nll": 14.829748153686523,
          "decoder_belief_top1_on_support": 0.1640625,
          "mean_decoder_belief_support_size": 3.7421875,
          "init_belief_target_mass": 0.9999985694885254,
          "init_belief_target_nll": 1.9459115266799927,
          "init_belief_top1_on_support": 1.0,
          "init_slot_relation_accuracy": 1.0,
          "init_slot_unique_a_frac": 1.0,
          "init_mixture_a_entropy": 1.945910096168518,
          "init_mixture_b_entropy": 1.945910096168518,
          "init_slot_a_overlap": 2.2507009589389781e-07,
          "init_slot_b_overlap": 2.2507009589389781e-07,
          "mean_slot_purity": 0.9999986290931702,
          "mean_slot_entropy": 2.3037249775370583e-05,
          "mean_weight_entropy": 1.9459102153778076,
          "mean_route_entropy": -1.0,
          "mean_route_accuracy": -1.0,
          "mean_target_support_size": 3.7421875
        },
        {
          "model": "end_to_end_structured_slot_executor",
          "variant": "smoke_oracle_primitive_router",
          "modulus": 7,
          "observe_mod": 3,
          "observe_prob": 0.3,
          "op_family": "full",
          "query_family": "all",
          "slot_capacity": 7,
          "init_mode": "oracle",
          "transition_mode": "primitive_router",
          "supervision": "full_belief",
          "slot_dim": 64,
          "hidden_dim": 128,
          "fourier_order": 8,
          "train_steps": 500,
          "length": 3,
          "query_type": "A_PLUS_B",
          "k": 1,
          "n": 128,
          "decoder_query_target_mass": 0.5390639305114746,
          "decoder_query_target_nll": 4.152556896209717,
          "decoder_query_top1_on_support": 0.5546875,
          "mean_decoder_query_support_size": 3.5859375,
          "decoder_belief_target_mass": 0.19977355003356934,
          "decoder_belief_target_nll": 12.359214782714844,
          "decoder_belief_top1_on_support": 0.203125,
          "mean_decoder_belief_support_size": 3.7421875,
          "init_belief_target_mass": 0.9999985694885254,
          "init_belief_target_nll": 1.9459115266799927,
          "init_belief_top1_on_support": 1.0,
          "init_slot_relation_accuracy": 1.0,
          "init_slot_unique_a_frac": 1.0,
          "init_mixture_a_entropy": 1.945910096168518,
          "init_mixture_b_entropy": 1.945910096168518,
          "init_slot_a_overlap": 2.2507009589389781e-07,
          "init_slot_b_overlap": 2.2507009589389781e-07,
          "mean_slot_purity": 0.8719894886016846,
          "mean_slot_entropy": 0.18799817562103271,
          "mean_weight_entropy": 1.5466687679290771,
          "mean_route_entropy": 0.0004461093049030751,
          "mean_route_accuracy": 1.0,
          "mean_target_support_size": 3.7421875
        },
        {
          "model": "end_to_end_structured_slot_executor",
          "variant": "smoke_oracle_primitive_router",
          "modulus": 7,
          "observe_mod": 3,
          "observe_prob": 0.3,
          "op_family": "full",
          "query_family": "all",
          "slot_capacity": 7,
          "init_mode": "oracle",
          "transition_mode": "primitive_router",
          "supervision": "full_belief",
          "slot_dim": 64,
          "hidden_dim": 128,
          "fourier_order": 8,
          "train_steps": 500,
          "length": 3,
          "query_type": "A_PLUS_B",
          "k": 2,
          "n": 128,
          "decoder_query_target_mass": 0.5531966686248779,
          "decoder_query_target_nll": 5.0676164627075195,
          "decoder_query_top1_on_support": 0.5859375,
          "mean_decoder_query_support_size": 3.5859375,
          "decoder_belief_target_mass": 0.34001392126083374,
          "decoder_belief_target_nll": 8.753302574157715,
          "decoder_belief_top1_on_support": 0.421875,
          "mean_decoder_belief_support_size": 3.7421875,
          "init_belief_target_mass": 0.9999985694885254,
          "init_belief_target_nll": 1.9459115266799927,
          "init_belief_top1_on_support": 1.0,
          "init_slot_relation_accuracy": 1.0,
          "init_slot_unique_a_frac": 1.0,
          "init_mixture_a_entropy": 1.945910096168518,
          "init_mixture_b_entropy": 1.945910096168518,
          "init_slot_a_overlap": 2.2507009589389781e-07,
          "init_slot_b_overlap": 2.2507009589389781e-07,
          "mean_slot_purity": 0.8261794447898865,
          "mean_slot_entropy": 0.3013455867767334,
          "mean_weight_entropy": 1.2971283197402954,
          "mean_route_entropy": 0.00044976314529776573,
          "mean_route_accuracy": 1.0,
          "mean_target_support_size": 3.7421875
        },
        {
          "model": "end_to_end_structured_slot_executor",
          "variant": "smoke_oracle_primitive_router",
          "modulus": 7,
          "observe_mod": 3,
          "observe_prob": 0.3,
          "op_family": "full",
          "query_family": "all",
          "slot_capacity": 7,
          "init_mode": "oracle",
          "transition_mode": "primitive_router",
          "supervision": "full_belief",
          "slot_dim": 64,
          "hidden_dim": 128,
          "fourier_order": 8,
          "train_steps": 500,
          "length": 3,
          "query_type": "A_PLUS_B",
          "k": 3,
          "n": 128,
          "decoder_query_target_mass": 0.9999325275421143,
          "decoder_query_target_nll": 1.0770909786224365,
          "decoder_query_top1_on_support": 1.0,
          "mean_decoder_query_support_size": 3.5859375,
          "decoder_belief_target_mass": 0.9998885989189148,
          "decoder_belief_target_nll": 1.131325125694275,
          "decoder_belief_top1_on_support": 1.0,
          "mean_decoder_belief_support_size": 3.7421875,
          "init_belief_target_mass": 0.9999985694885254,
          "init_belief_target_nll": 1.9459115266799927,
          "init_belief_top1_on_support": 1.0,
          "init_slot_relation_accuracy": 1.0,
          "init_slot_unique_a_frac": 1.0,
          "init_mixture_a_entropy": 1.945910096168518,
          "init_mixture_b_entropy": 1.945910096168518,
          "init_slot_a_overlap": 2.2507009589389781e-07,
          "init_slot_b_overlap": 2.2507009589389781e-07,
          "mean_slot_purity": 0.796413779258728,
          "mean_slot_entropy": 0.39494484663009644,
          "mean_weight_entropy": 1.1313207149505615,
          "mean_route_entropy": 0.000497039407491684,
          "mean_route_accuracy": 1.0,
          "mean_target_support_size": 3.7421875
        },
        {
          "model": "end_to_end_structured_slot_executor",
          "variant": "smoke_oracle_primitive_router",
          "modulus": 7,
          "observe_mod": 3,
          "observe_prob": 0.3,
          "op_family": "full",
          "query_family": "all",
          "slot_capacity": 7,
          "init_mode": "oracle",
          "transition_mode": "primitive_router",
          "supervision": "full_belief",
          "slot_dim": 64,
          "hidden_dim": 128,
          "fourier_order": 8,
          "train_steps": 500,
          "length": 3,
          "query_type": "A_MINUS_B",
          "k": 0,
          "n": 128,
          "decoder_query_target_mass": 0.4999999403953552,
          "decoder_query_target_nll": 12.593417167663574,
          "decoder_query_top1_on_support": 0.5,
          "mean_decoder_query_support_size": 3.3515625,
          "decoder_belief_target_mass": 0.10267852246761322,
          "decoder_belief_target_nll": 14.539328575134277,
          "decoder_belief_top1_on_support": 0.1484375,
          "mean_decoder_belief_support_size": 3.875,
          "init_belief_target_mass": 0.9999985694885254,
          "init_belief_target_nll": 1.9459115266799927,
          "init_belief_top1_on_support": 1.0,
          "init_slot_relation_accuracy": 1.0,
          "init_slot_unique_a_frac": 1.0,
          "init_mixture_a_entropy": 1.945910096168518,
          "init_mixture_b_entropy": 1.945910096168518,
          "init_slot_a_overlap": 2.2507009589389781e-07,
          "init_slot_b_overlap": 2.2507009589389781e-07,
          "mean_slot_purity": 0.9999986290931702,
          "mean_slot_entropy": 2.3037249775370583e-05,
          "mean_weight_entropy": 1.9459102153778076,
          "mean_route_entropy": -1.0,
          "mean_route_accuracy": -1.0,
          "mean_target_support_size": 3.875
        },
        {
          "model": "end_to_end_structured_slot_executor",
          "variant": "smoke_oracle_primitive_router",
          "modulus": 7,
          "observe_mod": 3,
          "observe_prob": 0.3,
          "op_family": "full",
          "query_family": "all",
          "slot_capacity": 7,
          "init_mode": "oracle",
          "transition_mode": "primitive_router",
          "supervision": "full_belief",
          "slot_dim": 64,
          "hidden_dim": 128,
          "fourier_order": 8,
          "train_steps": 500,
          "length": 3,
          "query_type": "A_MINUS_B",
          "k": 1,
          "n": 128,
          "decoder_query_target_mass": 0.4877240061759949,
          "decoder_query_target_nll": 7.477488040924072,
          "decoder_query_top1_on_support": 0.53125,
          "mean_decoder_query_support_size": 3.3515625,
          "decoder_belief_target_mass": 0.16089977324008942,
          "decoder_belief_target_nll": 12.11893367767334,
          "decoder_belief_top1_on_support": 0.2109375,
          "mean_decoder_belief_support_size": 3.875,
          "init_belief_target_mass": 0.9999985694885254,
          "init_belief_target_nll": 1.9459115266799927,
          "init_belief_top1_on_support": 1.0,
          "init_slot_relation_accuracy": 1.0,
          "init_slot_unique_a_frac": 1.0,
          "init_mixture_a_entropy": 1.945910096168518,
          "init_mixture_b_entropy": 1.945910096168518,
          "init_slot_a_overlap": 2.2507009589389781e-07,
          "init_slot_b_overlap": 2.2507009589389781e-07,
          "mean_slot_purity": 0.8805403113365173,
          "mean_slot_entropy": 0.17543140053749084,
          "mean_weight_entropy": 1.5728626251220703,
          "mean_route_entropy": 0.0004992071771994233,
          "mean_route_accuracy": 1.0,
          "mean_target_support_size": 3.875
        },
        {
          "model": "end_to_end_structured_slot_executor",
          "variant": "smoke_oracle_primitive_router",
          "modulus": 7,
          "observe_mod": 3,
          "observe_prob": 0.3,
          "op_family": "full",
          "query_family": "all",
          "slot_capacity": 7,
          "init_mode": "oracle",
          "transition_mode": "primitive_router",
          "supervision": "full_belief",
          "slot_dim": 64,
          "hidden_dim": 128,
          "fourier_order": 8,
          "train_steps": 500,
          "length": 3,
          "query_type": "A_MINUS_B",
          "k": 2,
          "n": 128,
          "decoder_query_target_mass": 0.583510160446167,
          "decoder_query_target_nll": 5.5555219650268555,
          "decoder_query_top1_on_support": 0.59375,
          "mean_decoder_query_support_size": 3.3515625,
          "decoder_belief_target_mass": 0.295931875705719,
          "decoder_belief_target_nll": 9.532023429870605,
          "decoder_belief_top1_on_support": 0.390625,
          "mean_decoder_belief_support_size": 3.875,
          "init_belief_target_mass": 0.9999985694885254,
          "init_belief_target_nll": 1.9459115266799927,
          "init_belief_top1_on_support": 1.0,
          "init_slot_relation_accuracy": 1.0,
          "init_slot_unique_a_frac": 1.0,
          "init_mixture_a_entropy": 1.945910096168518,
          "init_mixture_b_entropy": 1.945910096168518,
          "init_slot_a_overlap": 2.2507009589389781e-07,
          "init_slot_b_overlap": 2.2507009589389781e-07,
          "mean_slot_purity": 0.8399344086647034,
          "mean_slot_entropy": 0.272137850522995,
          "mean_weight_entropy": 1.32705819606781,
          "mean_route_entropy": 0.00043543154606595635,
          "mean_route_accuracy": 1.0,
          "mean_target_support_size": 3.875
        },
        {
          "model": "end_to_end_structured_slot_executor",
          "variant": "smoke_oracle_primitive_router",
          "modulus": 7,
          "observe_mod": 3,
          "observe_prob": 0.3,
          "op_family": "full",
          "query_family": "all",
          "slot_capacity": 7,
          "init_mode": "oracle",
          "transition_mode": "primitive_router",
          "supervision": "full_belief",
          "slot_dim": 64,
          "hidden_dim": 128,
          "fourier_order": 8,
          "train_steps": 500,
          "length": 3,
          "query_type": "A_MINUS_B",
          "k": 3,
          "n": 128,
          "decoder_query_target_mass": 0.9999301433563232,
          "decoder_query_target_nll": 0.8874931335449219,
          "decoder_query_top1_on_support": 1.0,
          "mean_decoder_query_support_size": 3.3515625,
          "decoder_belief_target_mass": 0.999879777431488,
          "decoder_belief_target_nll": 1.1526808738708496,
          "decoder_belief_top1_on_support": 1.0,
          "mean_decoder_belief_support_size": 3.875,
          "init_belief_target_mass": 0.9999985694885254,
          "init_belief_target_nll": 1.9459115266799927,
          "init_belief_top1_on_support": 1.0,
          "init_slot_relation_accuracy": 1.0,
          "init_slot_unique_a_frac": 1.0,
          "init_mixture_a_entropy": 1.945910096168518,
          "init_mixture_b_entropy": 1.945910096168518,
          "init_slot_a_overlap": 2.2507009589389781e-07,
          "init_slot_b_overlap": 2.2507009589389781e-07,
          "mean_slot_purity": 0.8152360320091248,
          "mean_slot_entropy": 0.34811580181121826,
          "mean_weight_entropy": 1.1526740789413452,
          "mean_route_entropy": 0.0004893376026302576,
          "mean_route_accuracy": 1.0,
          "mean_target_support_size": 3.875
        }
      ]
    }
  ],
  "checkpoints": [
    "large_artifacts/end_to_end_structured_slot_executor/checkpoints/smoke_oracle_primitive_router/checkpoint_final.pt"
  ],
  "num_parameters": 35402
}